aiowintest/__init__.py
aiowintest/packet.py
aiowintest/protocol.py
aiowintest/wintest_data.py
aiowintest-0.0.5.dist-info/LICENSE
aiowintest-0.0.5.dist-info/METADATA
aiowintest-0.0.5.dist-info/WHEEL
aiowintest-0.0.5.dist-info/top_level.txt
aiowintest-0.0.5.dist-info/RECORD
