Metadata-Version: 2.1
Name: aiowintest
Version: 0.0.5
Summary: Python implementation of the Win-Test UDP protocol
Home-page: https://github.com/hin/aiowintest
Author: Hans Insulander SM0UTY
Author-email: hans@codium.se
License: BSD 2-Clause "Simplified" License
Platform: UNKNOWN
Requires-Dist: asyncio
